{
    "subjects": {
        "e870c439-f806-11ec-ae76-7c70db79db90": {
            "ch_materia": 60,
            "descricao_materia": "Programação I",
            "tipo_ensino": 1
        },
        "0b08c899-f807-11ec-baa6-7c70db79db90": {
            "ch_materia": 60,
            "descricao_materia": "TCC I",
            "tipo_ensino": 1
        },
        "129c43ab-f807-11ec-b263-7c70db79db90": {
            "ch_materia": 60,
            "descricao_materia": "Redes I",
            "tipo_ensino": 1
        },
        "1a770f24-f807-11ec-9118-7c70db79db90": {
            "ch_materia": 120,
            "descricao_materia": "Programação",
            "tipo_ensino": 0
        },
        "253dbb95-f807-11ec-ac9a-7c70db79db90": {
            "ch_materia": 120,
            "descricao_materia": "Banco de Dados",
            "tipo_ensino": 0
        }
    },
    "gangs": {
        "2ac45349-f807-11ec-be5a-7c70db79db90": {
            "descricao_turma": "BSI1",
            "dt_inicio": "10/03/22",
            "dt_fim": "18/07/2022"
        },
        "30192744-f807-11ec-b2c6-7c70db79db90": {
            "descricao_turma": "BSI2",
            "dt_inicio": "03/08/22",
            "dt_fim": "15/12/2022"
        },
        "37353618-f807-11ec-a2fd-7c70db79db90": {
            "descricao_turma": "BSI7",
            "dt_inicio": "10/03/22",
            "dt_fim": "18/07/2022"
        },
        "3d0a5caa-f807-11ec-8b60-7c70db79db90": {
            "descricao_turma": "REDES1",
            "dt_inicio": "10/03/22",
            "dt_fim": "18/07/2022"
        },
        "410bc255-f807-11ec-841c-7c70db79db90": {
            "descricao_turma": "1info1",
            "dt_inicio": "16/02/22",
            "dt_fim": "15/12/2022"
        }
    },
    "courses": {
        "623d9d86-f807-11ec-bb60-7c70db79db90": {
            "nome_curso": "Bacharelado em Sistemas de Informação",
            "ch_curso": 2000
        },
        "6666f22f-f807-11ec-b6e4-7c70db79db90": {
            "nome_curso": "Redes",
            "ch_curso": 2000
        },
        "6a984261-f807-11ec-b1f8-7c70db79db90": {
            "nome_curso": "Técnico em Informática",
            "ch_curso": 1500
        }
    }
}